Workbook

Sheet Paramètres
A2: S : Prix du sous-jacent (spot) Type : float Exemple : 100.0 Description : Cours actuel de l’action ou de l’indice.
A4: # 2. K : Prix d’exercice (strike) Type : float Exemple : 100.0 Description : Niveau auquel tu as le droit d’acheter (call) ou vendre (put) à maturité.
A6: # 3. T : Maturité (en années) Type : float Exemple : 0.5 (pour 6 mois), 1.0 (pour 1 an) Description : Temps restant jusqu’à l’échéance, exprimé en fraction d’année.
A8: # 4. r : Taux sans risque (continu) Type : float Exemple : 0.02 (pour 2 %) Description : Taux d’intérêt sans risque annualisé, en continu (utilisé dans l’actualisation).
A10: # 5. q : Taux de dividende (continu) Type : float Exemple : 0.01 (pour 1 %), ou 0.0 si aucun dividende Description : Rendement du dividende annualisé, en continu.
A12: # 6. sigma : Volatilité (annualisée) Type : float Exemple : 0.20 (pour 20 %) Description : Volatilité du sous-jacent (implicite ou historique), annualisée.
A14: # 7. opt_type : Type d’option Type : str, valeurs possibles : "call" ou "put" Exemple : "call" Description : Précise si tu veux le prix
A23: Taux sans risque (Risk-Free Rate)
A25: Définition : C’est le rendement d’un actif considéré comme sans risque (souvent les obligations d’État à court terme).
A26: Caractère :
A27: Il n’est pas spécifique à une action, mais dépend du marché et de la devise.
A28: Exemple :
... A51: Taux de dividende = paramètre propre à l’action (ou à l’indice) sous-jacent.

Sheet Summary
A1: ISIN | B1: Description | C1: Position PV | D1: Position PV % | E1: PositionSize | F1: Price | G1: PV | H1: Ticker | I1: GovvieCurve.Ticker | J1: Position EDF PV | K1: Volume_avg_1m | L1: Volume_avg_3m | M1: Volume_avg_1y | N1: SandPIndustry | O1: Country | P1: AssetID | Q1: MarketCap | R1: Currency | S1: ReferencePortfolioCode | T1: IssuerName | U1: ParentCompanyName
A2: US67066G1040 | B2: NVIDIA (NVDA US, Common Stock) | C2: 760.32472 | D2: 7.6032472 | E2: 4.0768081 | F2: 186.5 | G2: 186.5 | H2: NVDA US | I2: EQ00iy2X | K2: 1.6308811e+08 | L2: 1.8550523e+08 | M2: 2.205305e+08 | N2: Electronics/electric | O2: United States | P2: EQ00iy2X | Q2: 4531950 | R2: USD | T2: NVIDIA CORP
A3: US0378331005 | B3: APPLE (AAPL US, Common Stock) | C3: 676.869 | D3: 6.7686901 | E3: 2.4897705 | F3: 271.86 | G3: 271.86 | H3: AAPL US | I3: EQ00JaUX | K3: 41072375 | L3: 45183906 | M3: 54119342 | N3: Electronics/electric | O3: United States | P3: EQ00JaUX | Q3: 4017099.3 | R3: USD | T3: APPLE INC
A4: US5949181045 | B4: MICROSOFT (MSFT US, Common Stock) | C4: 572.94866 | D4: 5.7294867 | E4: 1.1847084 | F4: 483.62 | G4: 483.62 | H4: MSFT US | I4: EQ00JdUX | K4: 22215005 | L4: 22526377 | M4: 22158498 | N4: Business equipment and services | O4: United States | P4: EQ00JdUX | Q4: 3594446.5 | R4: USD | T4: MICROSOFT CORP
A5: US0231351067 | B5: AMAZON.COM (AMZN US, Common Stock) | C5: 371.69543 | D5: 3.7169544 | E5: 1.6103259 | F5: 230.82 | G5: 230.82 | H5: AMZN US | I5: EQ00gVHX | K5: 35141425 | L5: 45161638 | M5: 44363514 | N5: Business equipment and services | O5: United States | P5: EQ00gVHX | Q5: 2467515.7 | R5: USD | T5: AMAZON.COM INC
A6: US02079K3059 | B6: ALPHABET (GOOGL US, Common Stock) | C6: 305.46215 | D6: 3.0546215 | E6: 0.9759174 | F6: 313 | G6: 313 | H6: GOOGL US | I6: EQ07RKsX | K6: 30618581 | L6: 35350575 | M6: 36185825 | N6: Business equipment and services | O6: United States | P6: EQ07RKsX | Q6: 2084580 | R6: USD | T6: ALPHABET INC
A7: US11135F1012 | B7: BROADCOM (AVGO US, Common Stock) | C7: 260.49462 | D7: 2.6049462 | E7: 0.75265709 | F7: 346.1 | G7: 346.1 | H7: AVGO US | I7: EQ09fnNX | K7: 38989101 | L7: 27935096 | M7: 26687758 | N7: Electronics/electric | O7: United States | P7: EQ09fnNX | Q7: 1640954.9 | R7: USD | T7: BROADCOM INC
A8: US02079K1079 | B8: ALPHABET (GOOG US, Common Stock) | C8: 257.28192 | D8: 2.5728193 | E8: 0.81989141 | F8: 313.8 | G8: 313.8 | H8: GOOG US | I8: EQ07RKvX | K8: 20071464 | L8: 22646986 | M8: 23513010 | N8: Business equipment and services | O8: United States | P8: EQ07RKvX | Q8: 1696716.6 | R8: USD | T8: ALPHABET INC
A9: US30303M1027 | B9: META PLATFORMS (META US, Common Stock) | C9: 240.29211 | D9: 2.4029212 | E9: 0.36402932 | F9: 660.09 | G9: 660.09 | H9: META US | I9: EQ0339GX | K9: 15056495 | L9: 18147513 | M9: 15458063 | N9: Business equipment and services | O9: United States | P9: EQ0339GX | Q9: 1663775.1 | R9: USD | T9: META PLATFORMS INC
A10: US88160R1014 | B10: TESLA (TSLA US, Common Stock) | C10: 213.24875 | D10: 2.1324875 | E10: 0.47418115 | F10: 449.72 | G10: 449.72 | H10: TSLA US | I10: EQ02hyEX | K10: 72704205 | L10: 82628174 | M10: 97651395 | N10: Automotive | O10: United States | P10: EQ02hyEX | Q10: 1495687.4 | R10: USD | T10: TESLA INC
A11: US46625H1005 | B11: JP MORGAN (JPM US, Common Stock) | C11: 148.64843 | D11: 1.4864843 | E11: 0.46132588 | F11: 322.22 | G11: 322.22 | H11: JPM US | I11: EQ00IWvX | K11: 9388615.2 | L11: 8662889.5 | M11: 9341214.8 | N11: Financial intermediaries | O11: United States | P11: EQ00IWvX | Q11: 886025.69 | R11: USD | T11: JPMORGAN CHASE & CO.
A12: US5324571083 | B12: LILLY (LLY US, Common Stock) | C12: 145.04838 | D12: 1.4504838 | E12: 0.1349689 | F12: 1074.68 | G12: 1074.68 | H12: LLY US | I12: EQ00IyDX | K12: 2983174.5 | L12: 3657666.1 | M12: 3963477.1 | N12: Drugs | O12: United States | P12: EQ00IyDX | Q12: 1015985 | R12: USD | T12: ELI LILLY & CO
A13: US0846707026 | B13: BERKSHIRE (BRK/B US, Common Stock) | C13: 116.25211 | D13: 1.1625211 | E13: 0.23127844 | F13: 502.65 | G13: 502.65 | H13: BRK/B US | I13: EQ00IQ3X | K13: 4275433.8 | L13: 4658128 | M13: 4757754.7 | N13: Property & Casualty Insurance | O13: United States | P13: EQ00IQ3X | Q13: 690048.04 | R13: USD | T13: BERKSHIRE HATHAWAY INC
... A408: US1270971039 | B408: COTERRA ENERGY (CTRA US, Common Stock) | C408: 3.3697996 | D408: 0.033697996 | E408: 0.1280319 | F408: 26.32 | G408: 26.32 | H408: CTRA US | I408: EQ00IUVX | K408: 6434910.4 | L408: 8655613 | M408: 7418991.3 | N408: Oil and gas | O408: United States | P408: EQ00IUVX | Q408: 20039.457 | R408: USD | T408: CABOT OIL & GAS
A409: US45784P1012 | B409: INSULET (PODD US, Common Stock) | C409: 3.3568033 | D409: 0.033568034 | E409: 0.01180975 | F409: 284.24 | G409: 284.24 | H409: PODD US | I409: EQ01MS8X | K409: 652245 | L409: 649447.12 | M409: 718499.47 | O409: United States | P409: EQ01MS8X | Q409: 19995.402 | R409: USD | T409: INSULET CORP
A410: US62944T1051 | B410: NVR (NVR US, Common Stock) | C410: 3.3356401 | D410: 0.033356401 | E410: 0.00045739 | F410: 7292.77 | G410: 7292.77 | H410: NVR US | I410: EQ00LF7X | K410: 20328.609 | L410: 21135.631 | M410: 22003.757 | N410: Building and development | O410: United States | P410: EQ00LF7X | Q410: 20707.325 | R410: USD | T410: NVR L.P.
A411: US9553061055 | B411: WEST PHARM SVC (WST US, Common Stock) | C411: 3.3192559 | D411: 0.03319256 | E411: 0.01206388 | F411: 275.14 | G411: 275.14 | H411: WST US | I411: EQ00JXCX | K411: 648814.35 | L411: 688659.63 | M411: 779627.08 | N411: Healthcare | O411: United States | P411: EQ00JXCX | Q411: 19794.51 | R411: USD | T411: WEST PHARMACEUTICAL SVCS
A412: US4601461035 | B412: INTL PAPER (IP US, Common Stock) | C412: 3.314689 | D412: 0.03314689 | E412: 0.08415052 | F412: 39.39 | G412: 39.39 | H412: IP US | I412: EQ00IuXX | K412: 4226543.3 | L412: 4787670.8 | M412: 5737541.9 | N412: Forest products | O412: United States | P412: EQ00IuXX | Q412: 20799.429 | R412: USD | T412: INTERNATIONAL PAPER CO.
A413: US65473P1057 | B413: NISOURCE (NI US, Common Stock) | C413: 3.2988433 | D413: 0.032988433 | E413: 0.07899529 | F413: 41.76 | G413: 41.76 | H413: NI US | I413: EQ00J5lX | K413: 3025103 | L413: 3776508.6 | M413: 4327523.4 | N413: Utilities | O413: United States | P413: EQ00J5lX | Q413: 19927.685 | R413: USD | T413: NISOURCE INC
A414: US74251V1026 | B414: PRINCIPAL FINCL (PFG US, Common Stock) | C414: 3.2967464 | D414: 0.032967464 | E414: 0.03737384 | F414: 88.21 | G414: 88.21 | H414: PFG US | I414: EQ00dt2X | K414: 1183179.8 | L414: 1239276.4 | M414: 1338729.9 | N414: Life Insurance | O414: United States | P414: EQ00dt2X | Q414: 19379.194 | R414: USD | T414: PRINCIPAL FINANCIAL GROUP INC
A415: US9022521051 | B415: TYLER TECH (TYL US, Common Stock) | C415: 3.2947827 | D415: 0.032947827 | E415: 0.00725803 | F415: 453.95 | G415: 453.95 | H415: TYL US | I415: EQ00JSDX | K415: 363463.7 | L415: 389853.86 | M415: 320404.22 | N415: Business equipment and services | O415: United States | P415: EQ00JSDX | Q415: 19532.437 | R415: USD | T415: TYLER TECHNOLOGIES INC
A416: US74834L1008 | B416: QUESTDIAGNOSTICS (DGX US, Common Stock) | C416: 3.2555287 | D416: 0.032555287 | E416: 0.01876061 | F416: 173.53 | G416: 173.53 | H416: DGX US | I416: EQ00fzIX | K416: 906983.35 | L416: 1075947.4 | M416: 1092710.9 | N416: Healthcare | O416: United States | P416: EQ00fzIX | Q416: 19303.887 | R416: USD | T416: QUEST DIAGNOSTIC INC
A417: US0937121079 | B417: BLOOM ENERGY (BE US, Common Stock) | C417: 3.2405556 | D417: 0.032405556 | E417: 0.03729492 | F417: 86.89 | G417: 86.89 | H417: BE US | I417: EQ09qvuX | K417: 11016332 | L417: 14032649 | M417: 9692011.8 | N417: Electronics/electric | O417: United States | P417: EQ09qvuX | Q417: 20550.42 | R417: USD | T417: BLOOM ENERGY CORP
A418: JE00BJ1F3079 | B418: AMCR (AMCR US, Common Stock) | C418: 3.2298591 | D418: 0.032298591 | E418: 0.38727327 | F418: 8.34 | G418: 8.34 | H418: AMCR US | I418: EQ00AW2J | K418: 16854681 | L418: 21711823 | M418: 26567682 | N418: Containers and glass products | O418: Switzerland | P418: EQ00AW2J | Q418: 19251.722 | R418: USD | T418: AMCOR PLC
A419: US4932671088 | B419: KEYCORP (KEY US, Common Stock) | C419: 3.2274351 | D419: 0.032274351 | E419: 0.15636798 | F419: 20.64 | G419: 20.64 | H419: KEY US | I419: EQ00Le2X | K419: 14988405 | L419: 18643169 | M419: 18759243 | N419: Financial intermediaries | O419: United States | P419: EQ00Le2X | Q419: 22557.86 | R419: USD | T419: KEYCORP
A420: US78467J1007 | B420: SS&C TECH HLDGS (SSNC US, Common Stock) | C420: 3.2236632 | D420: 0.032236632 | E420: 0.03687558 | F420: 87.42 | G420: 87.42 | H420: SSNC US | I420: EQ02fp1X | K420: 1132615.8 | L420: 1335192.3 | M420: 1332594.2 | N420: Business equipment and services | O420: United States | P420: EQ02fp1X | Q420: 21332.876 | R420: USD | T420: SS&C TECHNOLOGIES HOLDINGS INC
A421: US31946M1036 | B421: 1ST CITIZEN BANC (FCNCA US, Common Stock) | C421: 3.2178964 | D421: 0.032178965 | E421: 0.00149936 | F421: 2146.18 | G421: 2146.18 | H421: FCNCA US | I421: EQ00KUlX | K421: 81348.565 | L421: 105993.4 | M421: 103488.74 | N421: Financial intermediaries | O421: United States | P421: EQ00KUlX | Q421: 26688.933 | R421: USD | T421: FCB/NC CAPITAL TRUST I
... A544: US1156372096 | B544: BROWN FORMN (BF/B US, Common Stock) | C544: 0.79644207 | D544: 0.0079644208 | E544: 0.03056186 | F544: 26.06 | G544: 26.06 | H544: BF/B US | I544: EQ00ITmX | K544: 5356787.7 | L544: 4250184.2 | M544: 3917525.7 | N544: Beverage and tobacco | O544: United States | P544: EQ00ITmX | Q544: 7677.1373 | R544: USD | T544: BROWN-FORMAN CORPORATION

Sheet 50_BIGUS
A1: ISIN | B1: Description | C1: Position PV | D1: Position PV % | E1: PositionSize | F1: Price | G1: PV | H1: Ticker
A2: US67066G1040 | B2: NVIDIA (NVDA US, Common Stock) | C2: 760.32472 | D2: 7.6032472 | E2: 4.0768081 | F2: 186.5 | G2: 186.5 | H2: NVDA US
A3: US0378331005 | B3: APPLE (AAPL US, Common Stock) | C3: 676.869 | D3: 6.7686901 | E3: 2.4897705 | F3: 271.86 | G3: 271.86 | H3: AAPL US
A4: US5949181045 | B4: MICROSOFT (MSFT US, Common Stock) | C4: 572.94866 | D4: 5.7294867 | E4: 1.1847084 | F4: 483.62 | G4: 483.62 | H4: MSFT US
A5: US0231351067 | B5: AMAZON.COM (AMZN US, Common Stock) | C5: 371.69543 | D5: 3.7169544 | E5: 1.6103259 | F5: 230.82 | G5: 230.82 | H5: AMZN US
A6: US02079K3059 | B6: ALPHABET (GOOGL US, Common Stock) | C6: 305.46215 | D6: 3.0546215 | E6: 0.9759174 | F6: 313 | G6: 313 | H6: GOOGL US
A7: US11135F1012 | B7: BROADCOM (AVGO US, Common Stock) | C7: 260.49462 | D7: 2.6049462 | E7: 0.75265709 | F7: 346.1 | G7: 346.1 | H7: AVGO US
A8: US02079K1079 | B8: ALPHABET (GOOG US, Common Stock) | C8: 257.28192 | D8: 2.5728193 | E8: 0.81989141 | F8: 313.8 | G8: 313.8 | H8: GOOG US
A9: US30303M1027 | B9: META PLATFORMS (META US, Common Stock) | C9: 240.29211 | D9: 2.4029212 | E9: 0.36402932 | F9: 660.09 | G9: 660.09 | H9: META US
A10: US88160R1014 | B10: TESLA (TSLA US, Common Stock) | C10: 213.24875 | D10: 2.1324875 | E10: 0.47418115 | F10: 449.72 | G10: 449.72 | H10: TSLA US
A11: US46625H1005 | B11: JP MORGAN (JPM US, Common Stock) | C11: 148.64843 | D11: 1.4864843 | E11: 0.46132588 | F11: 322.22 | G11: 322.22 | H11: JPM US
A12: US5324571083 | B12: LILLY (LLY US, Common Stock) | C12: 145.04838 | D12: 1.4504838 | E12: 0.1349689 | F12: 1074.68 | G12: 1074.68 | H12: LLY US
A13: US0846707026 | B13: BERKSHIRE (BRK/B US, Common Stock) | C13: 116.25211 | D13: 1.1625211 | E13: 0.23127844 | F13: 502.65 | G13: 502.65 | H13: BRK/B US
... A50: US2546871060 | B50: WALT DISNEY (DIS US, Common Stock) | C50: 34.317486 | D50: 0.34317486 | E50: 0.30163915 | F50: 113.77 | G50: 113.77 | H50: DIS US

Sheet REQUETEEIKON
C1: =_xll.RDP.Data($B$3:$B$52,"TR.PriceClose;TR.AvgDailyVolume30D;TR.Volatility250D;TR.Volatility260D","CH=Fd RH=IN",C2) -> Updated at 11:58:00
D2: Price Close | E2: Average Daily Volume - 30 Days | F2: Volatility - 250 days | G2: Volatility - 260 days
A3: Ticker | B3: ISIN | C3: ISIN | D3: Unable to collect data for the field 'TR.PriceClose' and some specific identifier(s). | E3: Unable to collect data for the field 'TR.AvgDailyVolume30D' and some specific identifier(s). | F3: Unable to collect data for the field 'TR.Volatility250D' and some specific identifier(s). | G3: Unable to collect data for the field 'TR.Volatility260D' and some specific identifier(s).
A4: NVDA US | B4: US67066G1040 | C4: US67066G1040 | D4: 184.94 | E4: 41329178 | F4: 48.650881 | G4: 48.752166
A5: AAPL US | B5: US0378331005 | C5: US0378331005 | D5: 260.25 | E5: 16761257 | F5: 31.846932 | G5: 31.541674
A6: MSFT US | B6: US5949181045 | C6: US5949181045 | D6: 477.18 | E6: 8357423 | F6: 23.949319 | G6: 23.741677
A7: AMZN US | B7: US0231351067 | C7: US0231351067 | D7: 246.47 | E7: 12726401 | F7: 34.245598 | G7: 33.839868
A8: GOOGL US | B8: US02079K3059 | C8: US02079K3059 | D8: 331.86 | E8: 10872631 | F8: 31.99274 | G8: 31.616067
A9: AVGO US | B9: US11135F1012 | C9: US11135F1012 | D9: 352.21 | E9: 11920952 | F9: 52.937287 | G9: 52.218446
A10: GOOG US | B10: US02079K1079 | C10: US02079K1079 | D10: 332.73 | E10: 7171706 | F10: 31.573457 | G10: 31.207395
A11: META US | B11: US30303M1027 | C11: US30303M1027 | D11: 641.97 | E11: 4256927 | F11: 37.299632 | G11: 37.021262
A12: TSLA US | B12: US88160R1014 | C12: US88160R1014 | D12: 448.96 | E12: 15794319 | F12: 62.177291 | G12: 62.310955
A13: JPM US | B13: US46625H1005 | C13: US46625H1005 | D13: 324.49 | E13: 2909396 | F13: 25.156133 | G13: 24.86428
A14: LLY US | B14: US5324571083 | C14: US5324571083 | D14: 1081 | E14: 783344 | F14: 40.862713 | G14: 40.261476
A15: BRK/B US | B15: US0846707026 | C15: US0846707026 | D15: 498.67 | E15: 1463018 | F15: 18.584842 | G15: 18.402098
... A52: DIS US | B52: US2546871060 | C52: US2546871060 | D52: 112.82 | E52: 2645521 | F52: 29.771325 | G52: 29.283261

Sheet ZTk4MGVjYjMtZGQyYS00Yj
G5: AuditId=235970189_133446_STD_F271EEE9-6F5F-4E8F-9EB2-44B82A8AE3E5 | N5: AuditId=235970332_133446_STD_F271EEE9-6F5F-4E8F-9EB2-44B82A8AE3E5 | T5: AuditId=247832_133446_ANA_20916F21-15AE-410E-B7A9-1961F01B9BD4 | U5: AuditId=247421_133446_ANA_20916F21-15AE-410E-B7A9-1961F01B9BD4
G6: AuditId=297484566_19775_STD_3820D4EB-36FB-489A-BB97-F5A9A7AEAD56 | N6: AuditId=297484682_19775_STD_3820D4EB-36FB-489A-BB97-F5A9A7AEAD56 | T6: AuditId=383335_19775_ANA_02E328CC-6E3F-4389-8E11-32F53C8BE7EC | U6: AuditId=383349_19775_ANA_02E328CC-6E3F-4389-8E11-32F53C8BE7EC | V6: AuditId=383439_19775_ANA_26BD9B3E-8146-4952-A9C7-21E37AC1A90B | W6: AuditId=383443_19775_ANA_26BD9B3E-8146-4952-A9C7-21E37AC1A90B
N7: AuditId=297486533_19775_STD_71EB7D30-8C45-4D2A-9470-A04C418ACBA9
G8: AuditId=261953028_27602_STD_C724CA47-B4B6-4FB4-A09A-B5938A992717 | N8: AuditId=261953152_27602_STD_C724CA47-B4B6-4FB4-A09A-B5938A992717 | T8: AuditId=338820_27602_ANA_F70941D3-DE45-48A2-B8E0-0D1F9675D341 | U8: AuditId=339216_27602_ANA_F70941D3-DE45-48A2-B8E0-0D1F9675D341 | V8: AuditId=339211_27602_ANA_F70941D3-DE45-48A2-B8E0-0D1F9675D341 | W8: AuditId=339210_27602_ANA_F70941D3-DE45-48A2-B8E0-0D1F9675D341
N9: AuditId=242087017_114492_STD_6EBCF9C1-6F13-432C-BBD0-914A2E281706 | T9: AuditId=334922_114492_ANA_72B46BE2-D09D-4FA0-92C0-BA174582876D | U9: AuditId=334926_114492_ANA_72B46BE2-D09D-4FA0-92C0-BA174582876D
G10: AuditId=216006161_114888980_STD_24C3869B-2652-4F2A-ACC1-E8568517C007 | N10: AuditId=216006374_114888980_STD_24C3869B-2652-4F2A-ACC1-E8568517C007 | T10: AuditId=216075_114888980_ANA_EE9A86C1-BFE9-4B1C-B909-4742E48C9FD2 | U10: AuditId=216123_114888980_ANA_EE9A86C1-BFE9-4B1C-B909-4742E48C9FD2 | V10: AuditId=226031_114888980_ANA_AA5EA064-EA50-4FB6-9AF6-84651D4D73EB | W10: AuditId=226028_114888980_ANA_AA5EA064-EA50-4FB6-9AF6-84651D4D73EB
N11: AuditId=216006366_114888980_STD_24C3869B-2652-4F2A-ACC1-E8568517C007 | T11: AuditId=216064_114888980_ANA_EE9A86C1-BFE9-4B1C-B909-4742E48C9FD2 | U11: AuditId=216119_114888980_ANA_EE9A86C1-BFE9-4B1C-B909-4742E48C9FD2 | V11: AuditId=226032_114888980_ANA_AA5EA064-EA50-4FB6-9AF6-84651D4D73EB | W11: AuditId=226025_114888980_ANA_AA5EA064-EA50-4FB6-9AF6-84651D4D73EB
N12: AuditId=216006370_114888980_STD_24C3869B-2652-4F2A-ACC1-E8568517C007
G13: AuditId=290405654_116770864_STD_1B71F801-186D-4C73-AE51-EFE7F24160DB | N13: AuditId=290405756_116770864_STD_1B71F801-186D-4C73-AE51-EFE7F24160DB | T13: AuditId=151048_116770864_ANA_374F216F-3C17-4115-9983-9913D3BE5091 | U13: AuditId=151070_116770864_ANA_374F216F-3C17-4115-9983-9913D3BE5091 | V13: AuditId=151123_116770864_ANA_374F216F-3C17-4115-9983-9913D3BE5091 | W13: AuditId=151130_116770864_ANA_374F216F-3C17-4115-9983-9913D3BE5091
G14: AuditId=216006161_114888980_STD_24C3869B-2652-4F2A-ACC1-E8568517C007 | N14: AuditId=216006374_114888980_STD_24C3869B-2652-4F2A-ACC1-E8568517C007 | T14: AuditId=216075_114888980_ANA_EE9A86C1-BFE9-4B1C-B909-4742E48C9FD2 | U14: AuditId=216123_114888980_ANA_EE9A86C1-BFE9-4B1C-B909-4742E48C9FD2 | V14: AuditId=226031_114888980_ANA_AA5EA064-EA50-4FB6-9AF6-84651D4D73EB | W14: AuditId=226028_114888980_ANA_AA5EA064-EA50-4FB6-9AF6-84651D4D73EB
N15: AuditId=216006366_114888980_STD_24C3869B-2652-4F2A-ACC1-E8568517C007 | T15: AuditId=216064_114888980_ANA_EE9A86C1-BFE9-4B1C-B909-4742E48C9FD2 | U15: AuditId=216119_114888980_ANA_EE9A86C1-BFE9-4B1C-B909-4742E48C9FD2 | V15: AuditId=226032_114888980_ANA_AA5EA064-EA50-4FB6-9AF6-84651D4D73EB | W15: AuditId=226025_114888980_ANA_AA5EA064-EA50-4FB6-9AF6-84651D4D73EB
N16: AuditId=216006370_114888980_STD_24C3869B-2652-4F2A-ACC1-E8568517C007
G17: AuditId=239701386_102739130_STD_F61558F7-6BCD-4542-8F42-A05D7225A622 | N17: AuditId=239701525_102739130_STD_F61558F7-6BCD-4542-8F42-A05D7225A622 | T17: AuditId=138985_102739130_ANA_48F2B97F-54F6-4D35-A63D-1FF5D49C485C | U17: AuditId=139048_102739130_ANA_48F2B97F-54F6-4D35-A63D-1FF5D49C485C | V17: AuditId=143421_102739130_ANA_4922DA38-068F-4EDC-853F-5F756A22EF5B | W17: AuditId=143422_102739130_ANA_4922DA38-068F-4EDC-853F-5F756A22EF5B
N18: AuditId=239745374_102739130_STD_374AC42B-669A-4D54-99F7-BB5D3532A6D2
N19: AuditId=239745372_102739130_STD_374AC42B-669A-4D54-99F7-BB5D3532A6D2
N20: AuditId=239765416_103324829_STD_1B4F0F65-7E59-4390-8C1F-3DB391A81502 | T20: AuditId=160934_103324829_ANA_8604E691-0DAA-4114-BE3B-3867A7798A75 | U20: AuditId=160964_103324829_ANA_8604E691-0DAA-4114-BE3B-3867A7798A75 | V20: AuditId=166666_103324829_ANA_E5264DFD-C42C-4F5E-8FB5-B81AB5E5C878 | W20: AuditId=166668_103324829_ANA_E5264DFD-C42C-4F5E-8FB5-B81AB5E5C878
N21: AuditId=239765421_103324829_STD_1B4F0F65-7E59-4390-8C1F-3DB391A81502
N22: AuditId=239765425_103324829_STD_1B4F0F65-7E59-4390-8C1F-3DB391A81502
N23: AuditId=239765424_103324829_STD_1B4F0F65-7E59-4390-8C1F-3DB391A81502
N24: AuditId=239765423_103324829_STD_1B4F0F65-7E59-4390-8C1F-3DB391A81502
N25: AuditId=239765427_103324829_STD_1B4F0F65-7E59-4390-8C1F-3DB391A81502
G26: AuditId=237890139_21528_STD_4BF26B41-6D89-4D4F-B39C-7F473ED11172 | H26: AuditId=237890411_21528_STD_4BF26B41-6D89-4D4F-B39C-7F473ED11172 | N26: AuditId=237890393_21528_STD_4BF26B41-6D89-4D4F-B39C-7F473ED11172 | Q26: AuditId=237890486_21528_STD_4BF26B41-6D89-4D4F-B39C-7F473ED11172 | R26: AuditId=237890481_21528_STD_4BF26B41-6D89-4D4F-B39C-7F473ED11172 | T26: AuditId=1027479_21528_ANA_83AC3FF6-48A8-4690-B46C-AD0EE599A941 | U26: AuditId=1027774_21528_ANA_83AC3FF6-48A8-4690-B46C-AD0EE599A941 | V26: AuditId=1044082_21528_ANA_0EE18F3A-E7F9-43DA-B6BC-08491147C798 | W26: AuditId=1044083_21528_ANA_0EE18F3A-E7F9-43DA-B6BC-08491147C798
G27: AuditId=241900674_18231_STD_B15D84A9-9A0A-4DCC-990B-ED5B71D46207 | N27: AuditId=241900798_18231_STD_B15D84A9-9A0A-4DCC-990B-ED5B71D46207 | T27: AuditId=346329_18231_ANA_7D6E1258-31A3-4889-AC40-E8C073DD06F3 | U27: AuditId=346338_18231_ANA_7D6E1258-31A3-4889-AC40-E8C073DD06F3 | V27: AuditId=351225_18231_ANA_FA757548-08C1-4F37-8A61-92B3D82BDCBA | W27: AuditId=351226_18231_ANA_FA757548-08C1-4F37-8A61-92B3D82BDCBA
N28: AuditId=319663_20438_STD_CC5150A3-2BDA-4AA1-93FB-234247279405 | T28: AuditId=343547_20438_ANA_C0A4C4C8-7B4F-4317-8313-30C5338A9D92 | U28: AuditId=343271_20438_ANA_C0A4C4C8-7B4F-4317-8313-30C5338A9D92 | V28: AuditId=345922_20438_ANA_5855BFB7-0D5A-4746-BE57-EB79A3A71A50 | W28: AuditId=345913_20438_ANA_5855BFB7-0D5A-4746-BE57-EB79A3A71A50
N29: AuditId=319667_20438_STD_CC5150A3-2BDA-4AA1-93FB-234247279405 | T29: AuditId=343546_20438_ANA_C0A4C4C8-7B4F-4317-8313-30C5338A9D92 | U29: AuditId=343270_20438_ANA_C0A4C4C8-7B4F-4317-8313-30C5338A9D92 | V29: AuditId=345924_20438_ANA_5855BFB7-0D5A-4746-BE57-EB79A3A71A50 | W29: AuditId=345923_20438_ANA_5855BFB7-0D5A-4746-BE57-EB79A3A71A50

Sheet RATE EUR
A1: Fixing Date | B1: Start Date | C1: End Date | D1: Nb Days | E1: Rate | I1: SOFR | J1: Fixing Date | K1: Start Date | L1: End Date | M1: Nb Days | N1: Rate
A2: =B2 -> 46025 | B2: 46025 | C2: =B3 -> 46027 | D2: =C2-B2 -> 2 | E2: {=_xll.RDP.Data("EUROSTR=","TR.FixingValue","Sdate=#1",,A2)} -> 1.936 | F2: =1+D2/360*E2/100 -> 1.0001076 | J2: =K2 -> 46025 | K2: 46025 | L2: =K3 -> 46027 | M2: =L2-K2 -> 2 | N2: {=_xll.RDP.Data("USDSOFR=","TR.FixingValue","Sdate=#1",,J2)} -> 3.75 | O2: =1+M2/360*N2/100 -> 1.0002083 | R2: EU1YT=RR | S2: =_xll.RDP.Data("EU1YT=RR","TR.ASKYIELD","SDate=#1",,J$2) -> 1.961 | V2: US1YT=RR | W2: =_xll.RDP.Data("US1YT=RR","TR.ASKYIELD","SDate=#1",,J$2) -> 3.4613
A3: =B3 -> 46027 | B3: {=_xll.DfAddPeriod("EMu",B2,"1WD","RET:1")} -> 46027 | C3: =B4 -> 46028 | D3: =C3-B3 -> 1 | E3: {=_xll.RDP.Data("EUROSTR=","TR.FixingValue","Sdate=#1",,A3)} -> 1.933 | F3: =1+D3/360*E3/100 -> 1.0000537 | J3: =K3 -> 46027 | K3: {=_xll.DfAddPeriod("EMu",K2,"1WD","RET:1")} -> 46027 | L3: =K4 -> 46028 | M3: =L3-K3 -> 1 | N3: {=_xll.RDP.Data("USDSOFR=","TR.FixingValue","Sdate=#1",,J3)} -> 3.7 | O3: =1+M3/360*N3/100 -> 1.0001028 | R3: EU2YT=RR | S3: =_xll.RDP.Data("EU2YT=RR","TR.ASKYIELD","SDate=#1",,J$2) -> 2.128 | V3: US2YT=RR | W3: =_xll.RDP.Data("US2YT=RR","TR.ASKYIELD","SDate=#1",,J$2) -> 3.4754
A4: =B4 -> 46028 | B4: {=_xll.DfAddPeriod("EMu",B3,"1WD","RET:1")} -> 46028 | C4: =B5 -> 46029 | D4: =C4-B4 -> 1 | E4: {=_xll.RDP.Data("EUROSTR=","TR.FixingValue","Sdate=#1",,A4)} -> 1.933 | F4: =1+D4/360*E4/100 -> 1.0000537 | J4: =K4 -> 46028 | K4: {=_xll.DfAddPeriod("EMu",K3,"1WD","RET:1")} -> 46028 | L4: =K5 -> 46029 | M4: =L4-K4 -> 1 | N4: {=_xll.RDP.Data("USDSOFR=","TR.FixingValue","Sdate=#1",,J4)} -> 3.66 | O4: =1+M4/360*N4/100 -> 1.0001017 | R4: EU5YT=RR | S4: =_xll.RDP.Data("EU5YT=RR","TR.ASKYIELD","SDate=#1",,J$2) -> 2.473 | V4: US5YT=RR | W4: =_xll.RDP.Data("US5YT=RR","TR.ASKYIELD","SDate=#1",,J$2) -> 3.7427
A5: =B5 -> 46029 | B5: {=_xll.DfAddPeriod("EMu",B4,"1WD","RET:1")} -> 46029 | C5: =B6 -> 46030 | D5: =C5-B5 -> 1 | E5: {=_xll.RDP.Data("EUROSTR=","TR.FixingValue","Sdate=#1",,A5)} -> 1.933 | F5: =1+D5/360*E5/100 -> 1.0000537 | J5: =K5 -> 46029 | K5: {=_xll.DfAddPeriod("EMu",K4,"1WD","RET:1")} -> 46029 | L5: =K6 -> 46030 | M5: =L5-K5 -> 1 | N5: {=_xll.RDP.Data("USDSOFR=","TR.FixingValue","Sdate=#1",,J5)} -> 3.65 | O5: =1+M5/360*N5/100 -> 1.0001014 | R5: EU10YT=RR | S5: =_xll.RDP.Data("EU10YT=RR","TR.ASKYIELD","SDate=#1",,J$2) -> 2.897 | V5: US10YT=RR | W5: =_xll.RDP.Data("US10YT=RR","TR.ASKYIELD","SDate=#1",,J$2) -> 4.1926
A6: =B6 -> 46030 | B6: {=_xll.DfAddPeriod("EMu",B5,"1WD","RET:1")} -> 46030 | C6: =B7 -> 46031 | D6: =C6-B6 -> 1 | E6: {=_xll.RDP.Data("EUROSTR=","TR.FixingValue","Sdate=#1",,A6)} -> 1.933 | F6: =1+D6/360*E6/100 -> 1.0000537 | J6: =K6 -> 46030 | K6: {=_xll.DfAddPeriod("EMu",K5,"1WD","RET:1")} -> 46030 | L6: =K7 -> 46031 | M6: =L6-K6 -> 1 | N6: {=_xll.RDP.Data("USDSOFR=","TR.FixingValue","Sdate=#1",,J6)} -> 3.64 | O6: =1+M6/360*N6/100 -> 1.0001011 | R6: EU30YT=RR | S6: =_xll.RDP.Data("EU30YT=RR","TR.ASKYIELD","SDate=#1",,J$2) -> 3.536 | V6: US30YT=RR | W6: =_xll.RDP.Data("US30YT=RR","TR.ASKYIELD","SDate=#1",,J$2) -> 4.8702
A7: =B7 -> 46031 | B7: {=_xll.DfAddPeriod("EMu",B6,"1WD","RET:1")} -> 46031 | C7: =B8 -> 46034 | D7: =C7-B7 -> 3 | E7: {=_xll.RDP.Data("EUROSTR=","TR.FixingValue","Sdate=#1",,A7)} -> 1.932 | F7: =1+D7/360*E7/100 -> 1.000161 | J7: =K7 -> 46031 | K7: {=_xll.DfAddPeriod("EMu",K6,"1WD","RET:1")} -> 46031 | L7: =K8 -> 46034 | M7: =L7-K7 -> 3 | N7: {=_xll.RDP.Data("USDSOFR=","TR.FixingValue","Sdate=#1",,J7)} -> 3.64 | O7: =1+M7/360*N7/100 -> 1.0003033
A8: =B8 -> 46034 | B8: {=_xll.DfAddPeriod("EMu",B7,"1WD","RET:1")} -> 46034 | C8: =B9 -> 46035 | D8: =C8-B8 -> 1 | E8: {=_xll.RDP.Data("EUROSTR=","TR.FixingValue","Sdate=#1",,A8)} -> 1.931 | F8: =1+D8/360*E8/100 -> 1.0000536 | J8: =K8 -> 46034 | K8: {=_xll.DfAddPeriod("EMu",K7,"1WD","RET:1")} -> 46034 | L8: =K9 -> 46035 | M8: =L8-K8 -> 1 | N8: {=_xll.RDP.Data("USDSOFR=","TR.FixingValue","Sdate=#1",,J8)} -> 3.64 | O8: =1+M8/360*N8/100 -> 1.0001011 | S8: =S6/S2 -> 1.8031617 | W8: =W6/W2 -> 1.4070436
A9: =B9 -> 46035 | B9: {=_xll.DfAddPeriod("EMu",B8,"1WD","RET:1")} -> 46035 | C9: =B10 -> 46036 | D9: =C9-B9 -> 1 | E9: {=_xll.RDP.Data("EUROSTR=","TR.FixingValue","Sdate=#1",,A9)} -> 1.931 | F9: =1+D9/360*E9/100 -> 1.0000536 | J9: =K9 -> 46035 | K9: {=_xll.DfAddPeriod("EMu",K8,"1WD","RET:1")} -> 46035 | L9: =K10 -> 46036 | M9: =L9-K9 -> 1 | N9: {=_xll.RDP.Data("USDSOFR=","TR.FixingValue","Sdate=#1",,J9)} -> 3.64 | O9: =1+M9/360*N9/100 -> 1.0001011
A10: =B10 -> 46036 | B10: {=_xll.DfAddPeriod("EMu",B9,"1WD","RET:1")} -> 46036 | C10: =B11 -> 46037 | D10: =C10-B10 -> 1 | E10: {=_xll.RDP.Data("EUROSTR=","TR.FixingValue","Sdate=#1",,A10)} -> 1.931 | F10: =1+D10/360*E10/100 -> 1.0000536 | J10: =K10 -> 46036 | K10: {=_xll.DfAddPeriod("EMu",K9,"1WD","RET:1")} -> 46036 | L10: =K11 -> 46037 | M10: =L10-K10 -> 1 | N10: {=_xll.RDP.Data("USDSOFR=","TR.FixingValue","Sdate=#1",,J10)} -> 3.64 | O10: =1+M10/360*N10/100 -> 1.0001011
A11: =B11 -> 46037 | B11: {=_xll.DfAddPeriod("EMu",B10,"1WD","RET:1")} -> 46037 | C11: =B12 -> 46038 | D11: =C11-B11 -> 1 | E11: {=_xll.RDP.Data("EUROSTR=","TR.FixingValue","Sdate=#1",,A11)} -> 1.931 | F11: =1+D11/360*E11/100 -> 1.0000536 | J11: =K11 -> 46037 | K11: {=_xll.DfAddPeriod("EMu",K10,"1WD","RET:1")} -> 46037 | L11: =K12 -> 46038 | M11: =L11-K11 -> 1 | N11: {=_xll.RDP.Data("USDSOFR=","TR.FixingValue","Sdate=#1",,J11)} -> 3.64 | O11: =1+M11/360*N11/100 -> 1.0001011
A12: =B12 -> 46038 | B12: {=_xll.DfAddPeriod("EMu",B11,"1WD","RET:1")} -> 46038 | C12: =B13 -> 46041 | D12: =C12-B12 -> 3 | E12: {=_xll.RDP.Data("EUROSTR=","TR.FixingValue","Sdate=#1",,A12)} -> 1.931 | F12: =1+D12/360*E12/100 -> 1.0001609 | J12: =K12 -> 46038 | K12: {=_xll.DfAddPeriod("EMu",K11,"1WD","RET:1")} -> 46038 | L12: =K13 -> 46041 | M12: =L12-K12 -> 3 | N12: {=_xll.RDP.Data("USDSOFR=","TR.FixingValue","Sdate=#1",,J12)} -> 3.64 | O12: =1+M12/360*N12/100 -> 1.0003033
A13: =B13 -> 46041 | B13: {=_xll.DfAddPeriod("EMu",B12,"1WD","RET:1")} -> 46041 | C13: =B14 -> 46042 | D13: =C13-B13 -> 1 | E13: {=_xll.RDP.Data("EUROSTR=","TR.FixingValue","Sdate=#1",,A13)} -> 1.931 | F13: =1+D13/360*E13/100 -> 1.0000536 | J13: =K13 -> 46041 | K13: {=_xll.DfAddPeriod("EMu",K12,"1WD","RET:1")} -> 46041 | L13: =K14 -> 46042 | M13: =L13-K13 -> 1 | N13: {=_xll.RDP.Data("USDSOFR=","TR.FixingValue","Sdate=#1",,J13)} -> 3.64 | O13: =1+M13/360*N13/100 -> 1.0001011
A14: =B14 -> 46042 | B14: {=_xll.DfAddPeriod("EMu",B13,"1WD","RET:1")} -> 46042 | C14: =B15 -> 46043 | D14: =C14-B14 -> 1 | E14: {=_xll.RDP.Data("EUROSTR=","TR.FixingValue","Sdate=#1",,A14)} -> 1.931 | F14: =1+D14/360*E14/100 -> 1.0000536 | J14: =K14 -> 46042 | K14: {=_xll.DfAddPeriod("EMu",K13,"1WD","RET:1")} -> 46042 | L14: =K15 -> 46043 | M14: =L14-K14 -> 1 | N14: {=_xll.RDP.Data("USDSOFR=","TR.FixingValue","Sdate=#1",,J14)} -> 3.64 | O14: =1+M14/360*N14/100 -> 1.0001011
A15: =B15 -> 46043 | B15: {=_xll.DfAddPeriod("EMu",B14,"1WD","RET:1")} -> 46043 | C15: =B16 -> 46044 | D15: =C15-B15 -> 1 | E15: {=_xll.RDP.Data("EUROSTR=","TR.FixingValue","Sdate=#1",,A15)} -> 1.931 | F15: =1+D15/360*E15/100 -> 1.0000536 | J15: =K15 -> 46043 | K15: {=_xll.DfAddPeriod("EMu",K14,"1WD","RET:1")} -> 46043 | L15: =K16 -> 46044 | M15: =L15-K15 -> 1 | N15: {=_xll.RDP.Data("USDSOFR=","TR.FixingValue","Sdate=#1",,J15)} -> 3.64 | O15: =1+M15/360*N15/100 -> 1.0001011
A16: =B16 -> 46044 | B16: {=_xll.DfAddPeriod("EMu",B15,"1WD","RET:1")} -> 46044 | C16: =B17 -> 46045 | D16: =C16-B16 -> 1 | E16: {=_xll.RDP.Data("EUROSTR=","TR.FixingValue","Sdate=#1",,A16)} -> 1.931 | F16: =1+D16/360*E16/100 -> 1.0000536 | J16: =K16 -> 46044 | K16: {=_xll.DfAddPeriod("EMu",K15,"1WD","RET:1")} -> 46044 | L16: =K17 -> 46045 | M16: =L16-K16 -> 1 | N16: {=_xll.RDP.Data("USDSOFR=","TR.FixingValue","Sdate=#1",,J16)} -> 3.64 | O16: =1+M16/360*N16/100 -> 1.0001011
A17: =B17 -> 46045 | B17: {=_xll.DfAddPeriod("EMu",B16,"1WD","RET:1")} -> 46045 | C17: =B18 -> 46048 | D17: =C17-B17 -> 3 | E17: {=_xll.RDP.Data("EUROSTR=","TR.FixingValue","Sdate=#1",,A17)} -> 1.931 | F17: =1+D17/360*E17/100 -> 1.0001609 | J17: =K17 -> 46045 | K17: {=_xll.DfAddPeriod("EMu",K16,"1WD","RET:1")} -> 46045 | L17: =K18 -> 46048 | M17: =L17-K17 -> 3 | N17: {=_xll.RDP.Data("USDSOFR=","TR.FixingValue","Sdate=#1",,J17)} -> 3.64 | O17: =1+M17/360*N17/100 -> 1.0003033
A18: =B18 -> 46048 | B18: {=_xll.DfAddPeriod("EMu",B17,"1WD","RET:1")} -> 46048 | C18: =B19 -> 46049 | D18: =C18-B18 -> 1 | E18: {=_xll.RDP.Data("EUROSTR=","TR.FixingValue","Sdate=#1",,A18)} -> 1.931 | F18: =1+D18/360*E18/100 -> 1.0000536 | J18: =K18 -> 46048 | K18: {=_xll.DfAddPeriod("EMu",K17,"1WD","RET:1")} -> 46048 | L18: =K19 -> 46049 | M18: =L18-K18 -> 1 | N18: {=_xll.RDP.Data("USDSOFR=","TR.FixingValue","Sdate=#1",,J18)} -> 3.64 | O18: =1+M18/360*N18/100 -> 1.0001011
A19: =B19 -> 46049 | B19: {=_xll.DfAddPeriod("EMu",B18,"1WD","RET:1")} -> 46049 | C19: =B20 -> 46050 | D19: =C19-B19 -> 1 | E19: {=_xll.RDP.Data("EUROSTR=","TR.FixingValue","Sdate=#1",,A19)} -> 1.931 | F19: =1+D19/360*E19/100 -> 1.0000536 | J19: =K19 -> 46049 | K19: {=_xll.DfAddPeriod("EMu",K18,"1WD","RET:1")} -> 46049 | L19: =K20 -> 46050 | M19: =L19-K19 -> 1 | N19: {=_xll.RDP.Data("USDSOFR=","TR.FixingValue","Sdate=#1",,J19)} -> 3.64 | O19: =1+M19/360*N19/100 -> 1.0001011
A20: =B20 -> 46050 | B20: {=_xll.DfAddPeriod("EMu",B19,"1WD","RET:1")} -> 46050 | C20: =B21 -> 46051 | D20: =C20-B20 -> 1 | E20: {=_xll.RDP.Data("EUROSTR=","TR.FixingValue","Sdate=#1",,A20)} -> 1.931 | F20: =1+D20/360*E20/100 -> 1.0000536 | J20: =K20 -> 46050 | K20: {=_xll.DfAddPeriod("EMu",K19,"1WD","RET:1")} -> 46050 | L20: =K21 -> 46051 | M20: =L20-K20 -> 1 | N20: {=_xll.RDP.Data("USDSOFR=","TR.FixingValue","Sdate=#1",,J20)} -> 3.64 | O20: =1+M20/360*N20/100 -> 1.0001011
B21: {=_xll.DfAddPeriod("EMu",B20,"1WD","RET:1")} -> 46051 | K21: {=_xll.DfAddPeriod("EMu",K20,"1WD","RET:1")} -> 46051
E23: =SUM(E2:E20)/(C20-B2) -> 1.4116538 | F23: =ROUND((PRODUCT(F2:F20)-1)*36000/(C20-B2),6) -> 1.933064 | N23: =SUM(N2:N20)/(L20-K2) -> 2.6676923 | O23: =ROUND((PRODUCT(O2:O20)-1)*36000/(L20-K2),6) -> 3.656415

Sheet Dividendes
B3: ISIN | C3: =_xll.RDP.Data($B$4:$B$16,E3:X3,"CH=Fd RH=IN",C4) -> Updated at 11:58:00 | E3: AVAIL(TR.DividendYield(SDate=0D),TR.DividendYield(SDate=0D-1AD),TR.DividendYield(SDate=0D-2AD),TR.DividendYield(SDate=0D-3AD))/*Dividend Yield*/ | F3: AVG(TR.DividendYield(SDate=0D,EDate=0D-5AY,Frq=W))/*Dividend Yield 5 YR Avg*/ | G3: AVG(TR.DividendYield(SDate=0D,EDate=0D-10AY,Frq=W))/*Dividend Yield 10 YR Avg*/ | H3: TR.F.DivPaidCashTotCF | I3: TR.F.DistribForPrefShr | J3: TR.DPSMean | K3: TR.ANNUALIZEDDIVIDEND | L3: TR.F.DivToPolicyHold | M3: TR.F.ComprIncDivOnPrefStock | N3: TR.F.DPSSpecialIssue | O3: TR.F.DPSComGrossIssue | P3: TR.DPSSmartEst | Q3: TR.F.PriorityDivIssue | R3: TR.F.IntrDivIncExpnNetFin | S3: TR.F.IntrDivIncFinTot | T3: DIVIDEND | U3: TR.F.DivYldComStockIssuePct | V3: TR.F.DivYldComStockGrossIssuePct | W3: TR.F.DivYldComStockIssueByPrdEndDatePct | X3: TR.F.DivYldComStockGrossIssueByPrdEndDatePct
B4: US67066G1040 | D4: AVAIL(TR.DIVIDENDYIELD(SDATE=0D),TR.DIVIDENDYIELD(SDATE=0D-1AD),TR.DIVIDENDYIELD(SDATE=0D-2AD),TR.DIVIDENDYIELD(SDATE=0D-3AD))/*DIVIDEND YIELD*/ | E4: AVG(TR.DIVIDENDYIELD(SDATE=0D,EDATE=0D-5AY,FRQ=W))/*DIVIDEND YIELD 5 YR AVG*/ | F4: AVG(TR.DIVIDENDYIELD(SDATE=0D,EDATE=0D-10AY,FRQ=W))/*DIVIDEND YIELD 10 YR AVG*/ | G4: Dividends Paid - Cash - Total - Cash Flow | H4: Distribution for Preferred Shares | I4: Dividend Per Share - Mean | J4: Annualized Dividend | K4: Dividends to Policy Holders | L4: Comprehensive Income - Dividend on Preferred Stock | M4: DPS - Special - Gross - Issue - By Announcement Date | N4: DPS - Common - Gross - Issue - By Announcement Date | O4: Dividend Per Share - SmartEstimate® | P4: Priority Dividends - Issue Specific | Q4: Interest & Dividend Income/(Expense) - Net - Finance | R4: Interest & Dividend Income - Finance - Total | S4: Dividend | T4: Dividend Yield - Common - Net - Issue - % | U4: Dividend Yield - Common - Gross - Issue - % | V4: Dividend Yield - Common - Net - Issue - By Period End Date - % | W4: Dividend Yield - Common - Gross - Issue - By Period End Date - %
B5: US0378331005 | C5: US67066G1040 | D5: 0.021637996 | E5: 0.05601219 | F5: 0.2482665 | G5: 834000000 | H5: 0 | I5: 0.04001 | J5: 0 | K5: 0 | L5: 0 | M5: 0 | N5: 0.034 | O5: 0.04 | P5: 0 | Q5: 0 | R5: 0 | S5: The record could not be found (Error code: 0) | T5: 0.023839574 | U5: 0.023839574 | V5: 0 | W5: 0
B6: US5949181045 | C6: US0378331005 | D6: 0.40097158 | E6: 0.53677506 | F6: 1.0273773 | G6: 15421000000 | H6: 0 | I6: 1.06947 | J6: 0 | K6: 0 | L6: 0 | M6: 0 | N6: 1.02 | O6: 1.06883 | P6: 0 | Q6: 0 | R6: 0 | S6: The record could not be found (Error code: 0) | T6: 0.39927973 | U6: 0.39927973 | V6: 0.40319424 | W6: 0.40319424
B7: US0231351067 | C7: US0378331005 | D7: 0 | E7: 0 | F7: 0 | G7: 0 | H7: 0 | I7: 0 | J7: 0 | K7: 0 | L7: 0 | M7: 0 | N7: 0 | O7: 0 | P7: 0 | Q7: 0 | R7: 0 | S7: 0 | T7: 0 | U7: 0 | V7: 0 | W7: 0
B8: US02079K3059 | C8: US5949181045 | D8: 0.75947254 | E8: 0.83665785 | F8: 1.3321159 | G8: 24082000000 | H8: 0 | I8: 3.54385 | J8: 0 | K8: 0 | L8: 0 | M8: 0 | N8: 3.32 | O8: 3.57725 | P8: 0 | Q8: 0 | R8: 0 | S8: The record could not be found (Error code: 0) | T8: 0.66745743 | U8: 0.66745743 | V8: 0.66745743 | W8: 0.66745743
B9: US11135F1012 | C9: US0231351067 | D9: 0 | E9: 0 | F9: 0 | G9: 0 | H9: 0 | I9: 0 | J9: 0 | K9: 0 | L9: 0 | M9: 0 | N9: 0 | O9: 0 | P9: 0 | Q9: 0 | R9: 0 | S9: The record could not be found (Error code: 0) | T9: 0 | U9: 0 | V9: 0 | W9: 0
B10: US02079K1079 | C10: US02079K3059 | D10: 0.25565329 | E10: 0.43140842 | F10: 0.43140842 | G10: 7363000000 | H10: 0 | I10: 0.808 | J10: 0 | K10: 0 | L10: 0 | M10: 0 | N10: 0.6 | O10: 0.82994 | P10: 0 | Q10: 0 | R10: 0 | S10: The record could not be found (Error code: 0) | T10: 0.31505986 | U10: 0.31505986 | V10: 0.42007982 | W10: 0.42007982
B11: US30303M1027 | C11: US02079K3059 | D11: 0 | E11: 0 | F11: 0 | G11: 0 | H11: 0 | I11: 0 | J11: 0 | K11: 0 | L11: 0 | M11: 0 | N11: 0 | O11: 0 | P11: 0 | Q11: 0 | R11: 0 | S11: 0 | T11: 0.31695721 | U11: 0.31695721 | V11: 0.31695721 | W11: 0.31695721
B12: US88160R1014 | C12: US02079K3059 | D12: 0 | E12: 0 | F12: 0 | G12: 0 | H12: 0 | I12: 0 | J12: 0 | K12: 0 | L12: 0 | M12: 0 | N12: 0.6 | O12: 0 | P12: 0 | Q12: 0 | R12: 0 | S12: 0 | T12: 0 | U12: 0 | V12: 0 | W12: 0
B13: US46625H1005 | C13: US11135F1012 | D13: 0.75368873 | E13: 2.1503595 | F13: 2.5040417 | G13: 11142000000 | H13: 0 | I13: 2.69671 | J13: 0 | K13: 0 | L13: 0 | M13: 0 | N13: 2.36 | O13: 2.68049 | P13: 0 | Q13: 0 | R13: 0 | S13: The record could not be found (Error code: 0) | T13: 0.63847631 | U13: 0.63847631 | V13: 0.63847631 | W13: 0.63847631
B14: US5324571083 | C14: US02079K1079 | D14: 0.25565329 | E14: 0.43140842 | F14: 0.43140842 | G14: 7363000000 | H14: 0 | I14: 0.79714 | J14: 0 | K14: 0 | L14: 0 | M14: 0 | N14: 0.6 | O14: 0.828 | P14: 0 | Q14: 0 | R14: 0 | S14: The record could not be found (Error code: 0) | T14: 0.31505986 | U14: 0.31505986 | V14: 0.42007982 | W14: 0.42007982
B15: US0846707026 | C15: US02079K1079 | D15: 0 | E15: 0 | F15: 0 | G15: 0 | H15: 0 | I15: 0 | J15: 0 | K15: 0 | L15: 0 | M15: 0 | N15: 0 | O15: 0 | P15: 0 | Q15: 0 | R15: 0 | S15: 0 | T15: 0.31695721 | U15: 0.31695721 | V15: 0.31695721 | W15: 0.31695721
B16: US92826C8394 | C16: US02079K1079 | D16: 0 | E16: 0 | F16: 0 | G16: 0 | H16: 0 | I16: 0 | J16: 0 | K16: 0 | L16: 0 | M16: 0 | N16: 0.6 | O16: 0 | P16: 0 | Q16: 0 | R16: 0 | S16: 0 | T16: 0 | U16: 0 | V16: 0 | W16: 0
C17: US30303M1027 | D17: 0.3215631 | E17: 0.34977355 | F17: 0.34977355 | G17: 5072000000 | H17: 0 | I17: 2.11692 | J17: 0 | K17: 0 | L17: 0 | M17: 0 | N17: 2 | O17: 2.13318 | P17: 0 | Q17: 0 | R17: 0 | S17: The record could not be found (Error code: 0) | T17: 0.34158255 | U17: 0.34158255 | V17: 0.34158255 | W17: 0.34158255
C18: US30303M1027 | D18: 0 | E18: 0 | F18: 0 | G18: 0 | H18: 0 | I18: 0 | J18: 0 | K18: 0 | L18: 0 | M18: 0 | N18: 0 | O18: 0 | P18: 0 | Q18: 0 | R18: 0 | S18: 0 | T18: 0 | U18: 0 | V18: 0 | W18: 0
C19: US30303M1027 | D19: 0 | E19: 0 | F19: 0 | G19: 0 | H19: 0 | I19: 0 | J19: 0 | K19: 0 | L19: 0 | M19: 0 | N19: 0 | O19: 0 | P19: 0 | Q19: 0 | R19: 0 | S19: 0 | T19: 0 | U19: 0 | V19: 0 | W19: 0
C20: US88160R1014 | D20: 0 | E20: 0 | F20: 0 | G20: 0 | H20: 0 | I20: 0 | J20: 0 | K20: 0 | L20: 0 | M20: 0 | N20: 0 | O20: 0 | P20: 0 | Q20: 0 | R20: 0 | S20: The record could not be found (Error code: 0) | T20: 0 | U20: 0 | V20: 0 | W20: 0
C21: US88160R1014 | D21: 0 | E21: 0 | F21: 0 | G21: 0 | H21: 0 | I21: 0 | J21: 0 | K21: 0 | L21: 0 | M21: 0 | N21: 0 | O21: 0 | P21: 0 | Q21: 0 | R21: 0 | S21: 0 | T21: 0 | U21: 0 | V21: 0 | W21: 0
C22: US88160R1014 | D22: 0 | E22: 0 | F22: 0 | G22: 0 | H22: 0 | I22: 0 | J22: 0 | K22: 0 | L22: 0 | M22: 0 | N22: 0 | O22: 0 | P22: 0 | Q22: 0 | R22: 0 | S22: 0 | T22: 0 | U22: 0 | V22: 0 | W22: 0
C23: US88160R1014 | D23: 0 | E23: 0 | F23: 0 | G23: 0 | H23: 0 | I23: 0 | J23: 0 | K23: 0 | L23: 0 | M23: 0 | N23: 0 | O23: 0 | P23: 0 | Q23: 0 | R23: 0 | S23: 0 | T23: 0 | U23: 0 | V23: 0 | W23: 0
C24: US88160R1014 | D24: 0 | E24: 0 | F24: 0 | G24: 0 | H24: 0 | I24: 0 | J24: 0 | K24: 0 | L24: 0 | M24: 0 | N24: 0 | O24: 0 | P24: 0 | Q24: 0 | R24: 0 | S24: 0 | T24: 0 | U24: 0 | V24: 0 | W24: 0
C25: US88160R1014 | D25: 0 | E25: 0 | F25: 0 | G25: 0 | H25: 0 | I25: 0 | J25: 0 | K25: 0 | L25: 0 | M25: 0 | N25: 0 | O25: 0 | P25: 0 | Q25: 0 | R25: 0 | S25: 0 | T25: 0 | U25: 0 | V25: 0 | W25: 0
C26: US46625H1005 | D26: 1.8226556 | E26: 2.524342 | F26: 2.6524405 | G26: 14783000000 | H26: 1259000000 | I26: 5.82684 | J26: 0 | K26: 0 | L26: 0 | M26: 0 | N26: 4.8 | O26: 5.95272 | P26: 0 | Q26: 92583000000 | R26: 193933000000 | S26: The record could not be found (Error code: 0) | T26: 2.0024196 | U26: 2.0024196 | V26: 2.0024196 | W26: 2.0024196
C27: US5324571083 | D27: 0.650645 | E27: 1.0470691 | F27: 1.7140875 | G27: 4680400000 | H27: 0 | I27: 6.40536 | J27: 0 | K27: 0 | L27: 0 | M27: 0 | N27: 5.4 | O27: 6.74998 | P27: 0 | Q27: 0 | R27: 0 | S27: The record could not be found (Error code: 0) | T27: 0.69948187 | U27: 0.69948187 | V27: 0.67357513 | W27: 0.67357513
C28: US0846707026 | D28: 0 | E28: 0 | F28: 0 | G28: 0 | H28: 0 | I28: 0 | J28: 0 | K28: 0 | L28: 0 | M28: 0 | N28: 0 | O28: 0 | P28: 0 | Q28: 0 | R28: 0 | S28: The record could not be found (Error code: 0) | T28: 0 | U28: 0 | V28: 0 | W28: 0
C29: US0846707026 | D29: 0 | E29: 0 | F29: 0 | G29: 0 | H29: 0 | I29: 0 | J29: 0 | K29: 0 | L29: 0 | M29: 0 | N29: 0 | O29: 0 | P29: 0 | Q29: 0 | R29: 0 | S29: 0 | T29: 0 | U29: 0 | V29: 0 | W29: 0
C30: US92826C8394 | D30: 0.7662178 | E30: 0.72189167 | F30: 0.69949896 | G30: Unable to collect data for the field 'TR.F.DivPaidCashTotCF' and some specific identifier(s). | H30: Unable to collect data for the field 'TR.F.DistribForPrefShr' and some specific identifier(s). | I30: 2.69032 | J30: 0 | K30: Unable to collect data for the field 'TR.F.DivToPolicyHold' and some specific identifier(s). | L30: Unable to collect data for the field 'TR.F.ComprIncDivOnPrefStock' and some specific identifier(s). | M30: Unable to collect data for the field 'TR.F.DPSSpecialIssue' and some specific identifier(s). | N30: Unable to collect data for the field 'TR.F.DPSComGrossIssue' and some specific identifier(s). | O30: 2.75128 | P30: Unable to collect data for the field 'TR.F.PriorityDivIssue' and some specific identifier(s). | Q30: Unable to collect data for the field 'TR.F.IntrDivIncExpnNetFin' and some specific identifier(s). | R30: Unable to collect data for the field 'TR.F.IntrDivIncFinTot' and some specific identifier(s). | S30: The record could not be found (Error code: 0) | T30: Unable to collect data for the field 'TR.F.DivYldComStockIssuePct' and some specific identifier(s). | U30: Unable to collect data for the field 'TR.F.DivYldComStockGrossIssuePct' and some specific identifier(s). | V30: Unable to collect data for the field 'TR.F.DivYldComStockIssueByPrdEndDatePct' and some specific identifier(s). | W30: Unable to collect data for the field 'TR.F.DivYldComStockGrossIssueByPrdEndDatePct' and some specific identifier(s).

Sheet Equity
A1: Description | B1: PositionSize | C1: Ticker | D1: Currency | E1: Volume_avg_3m | F1: PV
A2: CBRE GROUP (CBRE US, Common Stock) | B2: 0.04992065 | C2: CBRE US | D2: USD | E2: 1446254.1 | F2: 160.79
A3: DIGITAL REALTY (DLR US, Common Stock) | B3: 0.05721799 | C3: DLR US | D3: USD | E3: 1821259.7 | F3: 154.71
A4: DEXCOM (DXCM US, Common Stock) | B4: 0.06579184 | C4: DXCM US | D4: USD | E4: 5813858.9 | F4: 66.37
A5: LINDE (LIN US, Common Stock) | B5: 0.0786689 | C5: LIN US | D5: USD | E5: 2663317.5 | F5: 426.39
A6: FOX (FOX US, Common Stock) | B6: 0.02569021 | C6: FOX US | D6: USD | E6: 1450117.6 | F6: 64.93
A7: TRADEWEB MARKETS (TW US, Common Stock) | B7: 0.01953742 | C7: TW US | D7: USD | E7: 1351342.9 | F7: 107.54
A8: CROWDSTRIKE HLDG (CRWD US, Common Stock) | B8: 0.04210271 | C8: CRWD US | D8: USD | E8: 2282188.8 | F8: 468.76
A9: DYNATRACE (DT US, Common Stock) | B9: 0.05058367 | C9: DT US | D9: USD | E9: 3268453.8 | F9: 43.34
A10: PALANTIR TECH (PLTR US, Common Stock) | B10: 0.38178824 | C10: PLTR US | D10: USD | E10: 47481374 | F10: 177.75
A11: ROCKET LAB (RKLB US, Common Stock) | B11: 0.0733566 | C11: RKLB US | D11: USD | E11: 23060502 | F11: 69.76
A12: ROBLOX CORP (RBLX US, Common Stock) | B12: 0.09756801 | C12: RBLX US | D12: USD | E12: 7458598.7 | F12: 81.03
A13: LIVE NATION (LYV US, Common Stock) | B13: 0.02719205 | C13: LYV US | D13: USD | E13: 3009349.5 | F13: 142.5
... A544: CARVANA (CVNA US, Common Stock) | B544: 0.02200794 | C544: CVNA US | D544: USD | E544: 3931203.9 | F544: 422.02

Sheet SORTIE
A1: TICKER | B1: S | C1: K | D1: T | E1: r | F1: q | G1: sigma | H1: Tyopt
A2: =REQUETEEIKON!A4 -> NVDA US | B2: =REQUETEEIKON!D4 -> 184.94 | C2: =0.75*B2 -> 138.705 | D2: =(I$2-J$2)/365.25 -> 0.90349076 | E2: ='RATE EUR'!N$2 -> 3.75 | F2: 0 | G2: =REQUETEEIKON!G4/100 -> 0.48752166 | H2: call | I2: 46365 | J2: =TODAY() -> 46035 | K2: =I2-J2 -> 330
A3: =REQUETEEIKON!A5 -> AAPL US | B3: =REQUETEEIKON!D5 -> 260.25 | C3: =0.75*B3 -> 195.1875 | D3: =(I$2-J$2)/365.25 -> 0.90349076 | E3: ='RATE EUR'!N$2 -> 3.75 | F3: 0 | G3: =REQUETEEIKON!G5/100 -> 0.31541674 | H3: call | M3: S : Prix du sous-jacent (spot) Type : float Exemple : 100.0 Description : Cours actuel de l’action ou de l’indice.
A4: =REQUETEEIKON!A6 -> MSFT US | B4: =REQUETEEIKON!D6 -> 477.18 | C4: =0.75*B4 -> 357.885 | D4: =(I$2-J$2)/365.25 -> 0.90349076 | E4: ='RATE EUR'!N$2 -> 3.75 | F4: 0 | G4: =REQUETEEIKON!G6/100 -> 0.23741677 | H4: call
A5: =REQUETEEIKON!A7 -> AMZN US | B5: =REQUETEEIKON!D7 -> 246.47 | C5: =0.75*B5 -> 184.8525 | D5: =(I$2-J$2)/365.25 -> 0.90349076 | E5: ='RATE EUR'!N$2 -> 3.75 | F5: 0 | G5: =REQUETEEIKON!G7/100 -> 0.33839868 | H5: call | M5: # 2. K : Prix d’exercice (strike) Type : float Exemple : 100.0 Description : Niveau auquel tu as le droit d’acheter (call) ou vendre (put) à maturité.
A6: =REQUETEEIKON!A8 -> GOOGL US | B6: =REQUETEEIKON!D8 -> 331.86 | C6: =0.75*B6 -> 248.895 | D6: =(I$2-J$2)/365.25 -> 0.90349076 | E6: ='RATE EUR'!N$2 -> 3.75 | F6: 0 | G6: =REQUETEEIKON!G8/100 -> 0.31616067 | H6: call
A7: =REQUETEEIKON!A9 -> AVGO US | B7: =REQUETEEIKON!D9 -> 352.21 | C7: =0.75*B7 -> 264.1575 | D7: =(I$2-J$2)/365.25 -> 0.90349076 | E7: ='RATE EUR'!N$2 -> 3.75 | F7: 0 | G7: =REQUETEEIKON!G9/100 -> 0.52218446 | H7: call | M7: # 3. T : Maturité (en années) Type : float Exemple : 0.5 (pour 6 mois), 1.0 (pour 1 an) Description : Temps restant jusqu’à l’échéance, exprimé en fraction d’année.
A8: =REQUETEEIKON!A10 -> GOOG US | B8: =REQUETEEIKON!D10 -> 332.73 | C8: =0.75*B8 -> 249.5475 | D8: =(I$2-J$2)/365.25 -> 0.90349076 | E8: ='RATE EUR'!N$2 -> 3.75 | F8: 0 | G8: =REQUETEEIKON!G10/100 -> 0.31207395 | H8: call
A9: =REQUETEEIKON!A11 -> META US | B9: =REQUETEEIKON!D11 -> 641.97 | C9: =0.75*B9 -> 481.4775 | D9: =(I$2-J$2)/365.25 -> 0.90349076 | E9: ='RATE EUR'!N$2 -> 3.75 | F9: 0 | G9: =REQUETEEIKON!G11/100 -> 0.37021262 | H9: call | M9: # 4. r : Taux sans risque (continu) Type : float Exemple : 0.02 (pour 2 %) Description : Taux d’intérêt sans risque annualisé, en continu (utilisé dans l’actualisation).
A10: =REQUETEEIKON!A12 -> TSLA US | B10: =REQUETEEIKON!D12 -> 448.96 | C10: =0.75*B10 -> 336.72 | D10: =(I$2-J$2)/365.25 -> 0.90349076 | E10: ='RATE EUR'!N$2 -> 3.75 | F10: 0 | G10: =REQUETEEIKON!G12/100 -> 0.62310955 | H10: call
A11: =REQUETEEIKON!A13 -> JPM US | B11: =REQUETEEIKON!D13 -> 324.49 | C11: =0.75*B11 -> 243.3675 | D11: =(I$2-J$2)/365.25 -> 0.90349076 | E11: ='RATE EUR'!N$2 -> 3.75 | F11: 0 | G11: =REQUETEEIKON!G13/100 -> 0.2486428 | H11: call | M11: # 5. q : Taux de dividende (continu) Type : float Exemple : 0.01 (pour 1 %), ou 0.0 si aucun dividende Description : Rendement du dividende annualisé, en continu.
A12: =REQUETEEIKON!A14 -> LLY US | B12: =REQUETEEIKON!D14 -> 1081 | C12: =0.75*B12 -> 810.75 | D12: =(I$2-J$2)/365.25 -> 0.90349076 | E12: ='RATE EUR'!N$2 -> 3.75 | F12: 0 | G12: =REQUETEEIKON!G14/100 -> 0.40261476 | H12: call
A13: =REQUETEEIKON!A15 -> BRK/B US | B13: =REQUETEEIKON!D15 -> 498.67 | C13: =0.75*B13 -> 374.0025 | D13: =(I$2-J$2)/365.25 -> 0.90349076 | E13: ='RATE EUR'!N$2 -> 3.75 | F13: 0 | G13: =REQUETEEIKON!G15/100 -> 0.18402098 | H13: call | M13: # 6. sigma : Volatilité (annualisée) Type : float Exemple : 0.20 (pour 20 %) Description : Volatilité du sous-jacent (implicite ou historique), annualisée.
A14: =REQUETEEIKON!A16 -> V US | B14: =REQUETEEIKON!D16 -> 343.2 | C14: =0.75*B14 -> 257.4 | D14: =(I$2-J$2)/365.25 -> 0.90349076 | E14: ='RATE EUR'!N$2 -> 3.75 | F14: 0 | G14: =REQUETEEIKON!G16/100 -> 0.22303871 | H14: call
A15: =REQUETEEIKON!A17 -> XOM US | B15: =REQUETEEIKON!D17 -> 124.03 | C15: =0.75*B15 -> 93.0225 | D15: =(I$2-J$2)/365.25 -> 0.90349076 | E15: ='RATE EUR'!N$2 -> 3.75 | F15: 0 | G15: =REQUETEEIKON!G17/100 -> 0.23951531 | H15: call | M15: # 7. opt_type : Type d’option Type : str, valeurs possibles : "call" ou "put" Exemple : "call" Description : Précise si tu veux le prix
A16: =REQUETEEIKON!A18 -> JNJ US | B16: =REQUETEEIKON!D18 -> 209.72 | C16: =0.75*B16 -> 157.29 | D16: =(I$2-J$2)/365.25 -> 0.90349076 | E16: ='RATE EUR'!N$2 -> 3.75 | F16: 0 | G16: =REQUETEEIKON!G18/100 -> 0.19484176 | H16: call
A17: =REQUETEEIKON!A19 -> WMT US | B17: =REQUETEEIKON!D19 -> 117.97 | C17: =0.75*B17 -> 88.4775 | D17: =(I$2-J$2)/365.25 -> 0.90349076 | E17: ='RATE EUR'!N$2 -> 3.75 | F17: 0 | G17: =REQUETEEIKON!G19/100 -> 0.24702633 | H17: call
A18: =REQUETEEIKON!A20 -> MA US | B18: =REQUETEEIKON!D20 -> 566.28 | C18: =0.75*B18 -> 424.71 | D18: =(I$2-J$2)/365.25 -> 0.90349076 | E18: ='RATE EUR'!N$2 -> 3.75 | F18: 0 | G18: =REQUETEEIKON!G20/100 -> 0.22486311 | H18: call
A19: =REQUETEEIKON!A21 -> PLTR US | B19: =REQUETEEIKON!D21 -> 179.41 | C19: =0.75*B19 -> 134.5575 | D19: =(I$2-J$2)/365.25 -> 0.90349076 | E19: ='RATE EUR'!N$2 -> 3.75 | F19: 0 | G19: =REQUETEEIKON!G21/100 -> 0.65509324 | H19: call
A20: =REQUETEEIKON!A22 -> ABBV US | B20: =REQUETEEIKON!D22 -> 220.04 | C20: =0.75*B20 -> 165.03 | D20: =(I$2-J$2)/365.25 -> 0.90349076 | E20: ='RATE EUR'!N$2 -> 3.75 | F20: 0 | G20: =REQUETEEIKON!G22/100 -> 0.26603844 | H20: call
A21: =REQUETEEIKON!A23 -> NFLX US | B21: =REQUETEEIKON!D23 -> 89.41 | C21: =0.75*B21 -> 67.0575 | D21: =(I$2-J$2)/365.25 -> 0.90349076 | E21: ='RATE EUR'!N$2 -> 3.75 | F21: 0 | G21: =REQUETEEIKON!G23/100 -> 0.33464724 | H21: call
A22: =REQUETEEIKON!A24 -> BAC US | B22: =REQUETEEIKON!D24 -> 55.19 | C22: =0.75*B22 -> 41.3925 | D22: =(I$2-J$2)/365.25 -> 0.90349076 | E22: ='RATE EUR'!N$2 -> 3.75 | F22: 0 | G22: =REQUETEEIKON!G24/100 -> 0.26718187 | H22: call
A23: =REQUETEEIKON!A25 -> COST US | B23: =REQUETEEIKON!D25 -> 943.08 | C23: =0.75*B23 -> 707.31 | D23: =(I$2-J$2)/365.25 -> 0.90349076 | E23: ='RATE EUR'!N$2 -> 3.75 | F23: 0 | G23: =REQUETEEIKON!G25/100 -> 0.21903126 | H23: call
A24: =REQUETEEIKON!A26 -> AMD US | B24: =REQUETEEIKON!D26 -> 207.69 | C24: =0.75*B24 -> 155.7675 | D24: =(I$2-J$2)/365.25 -> 0.90349076 | E24: ='RATE EUR'!N$2 -> 3.75 | F24: 0 | G24: =REQUETEEIKON!G26/100 -> 0.57779957 | H24: call
A25: =REQUETEEIKON!A27 -> HD US | B25: =REQUETEEIKON!D27 -> 374.94 | C25: =0.75*B25 -> 281.205 | D25: =(I$2-J$2)/365.25 -> 0.90349076 | E25: ='RATE EUR'!N$2 -> 3.75 | F25: 0 | G25: =REQUETEEIKON!G27/100 -> 0.23317882 | H25: call
A26: =REQUETEEIKON!A28 -> PG US | B26: =REQUETEEIKON!D28 -> 143.46 | C26: =0.75*B26 -> 107.595 | D26: =(I$2-J$2)/365.25 -> 0.90349076 | E26: ='RATE EUR'!N$2 -> 3.75 | F26: 0 | G26: =REQUETEEIKON!G28/100 -> 0.18968306 | H26: call
A27: =REQUETEEIKON!A29 -> ORCL US | B27: =REQUETEEIKON!D29 -> 204.68 | C27: =0.75*B27 -> 153.51 | D27: =(I$2-J$2)/365.25 -> 0.90349076 | E27: ='RATE EUR'!N$2 -> 3.75 | F27: 0 | G27: =REQUETEEIKON!G29/100 -> 0.5785618 | H27: call
... A50: =REQUETEEIKON!A52 -> DIS US | B50: =REQUETEEIKON!D52 -> 112.82 | C50: =0.75*B50 -> 84.615 | D50: =(I$2-J$2)/365.25 -> 0.90349076 | E50: ='RATE EUR'!N$2 -> 3.75 | F50: 0 | G50: =REQUETEEIKON!G52/100 -> 0.29283261 | H50: call

Sheet OPW
A1: Bonjour Guillaume,
A3: Pour récupérer les RIC des listed options, je vous suggère l’ APP « Options Watch » (cf shortcut = OPW) (Voir exemple ci-dessous)
A46: Vous avez accès à un pricer d’option (cf shortcut= OPR) (Voir exemple sur NVIDIA avec un focus sur les dividendes)
